{
  "ciuman": [":*", ":-*", ":x", "*:", "*-:", "x:"],
  "senang": [
    ":-)",
    ":-))",
    ":-)))",
    ":-))))",
    ":-)))))",
    ":-))))))",
    ":)",
    ":))",
    ":)))",
    ":))))",
    ":)))))",
    ":))))))",
    ":)))))))",
    ":o)",
    ":]",
    ":3",
    ":c)",
    ":>",
    "=]",
    "8)",
    "=)",
    ":}",
    ":^)",
    "|;-)",
    ":'-)",
    ":')",
    "\\o/",
    "*\\0/*",
    "(-:",
    "((-:",
    "(((-:",
    "((((-:",
    "(((((-:",
    "((((((-:",
    "(:",
    "((:",
    "(((:",
    "((((:",
    "(((((:",
    "((((((:",
    "(((((((:",
    "(o:",
    "[:",
    "<:",
    "[=",
    "(=",
    "{:",
    "(-':",
    "(':"
  ],
  "tertawa": [
    ":-D",
    ":D",
    "8-D",
    "8D",
    "x-D",
    "xD",
    "X-D",
    "XD",
    "=-D",
    "=D",
    "=-3",
    "=3",
    "B^D",
    ":-d",
    ":d",
    "8-d",
    "8d",
    "x-d",
    "xd",
    "=-d",
    "=d",
    "b^d"
  ],
  "sedih": [
    ">:[",
    ":-(",
    ":-((",
    ":-(((",
    ":-((((",
    ":-(((((",
    ":-((((((",
    ":-(((((((",
    ":(",
    ":((",
    ":(((",
    ":((((",
    ":(((((",
    ":((((((",
    ":(((((((",
    ":((((((((",
    ":-c",
    ":c",
    ":-<",
    ":<",
    ":-[",
    ":[",
    ":{",
    ":-||",
    ":@",
    ":'-(",
    ":'(",
    "D:<",
    "D:",
    "D8",
    "D;",
    "D=",
    "DX",
    "v.v",
    "D-':",
    "(>_<)",
    ":|",
    "]:<",
    ")-:",
    "))-:",
    ")))-:",
    "))))-:",
    ")))))-:",
    "))))))-:",
    ")))))))-:",
    "):",
    ")):",
    "))):",
    ")))):",
    "))))):",
    ")))))):",
    "))))))):",
    ")))))))):",
    ">-:",
    ">:",
    "]-:",
    "]:",
    "}:",
    "||-:",
    "@:",
    ")-':",
    ")':",
    "|:",
    "d:<",
    "d:",
    "d8",
    "d;",
    "d=",
    "dx",
    "d-':"
  ],
  "kejutan": [
    ">:O",
    ":-O",
    ":-o",
    ":O",
    "°o°",
    "o_O",
    "o_0",
    "o.O",
    "o-o",
    "8-0",
    "|-O",
    "O:<",
    "O-:",
    "o-:",
    "O:",
    ">:o",
    ":o",
    "o_o",
    "o.o",
    "|-o",
    "o:<",
    "o:"
  ],
  "mengedip": [";-)", ";)", "*-)", "*)", ";-]", ";]", ";D", ";^)", ":-,", ";d"],
  "lidah": [
    ">:P",
    ":-P",
    ":P",
    "X-P",
    "x-p",
    "xp",
    "XP",
    ":-p",
    ":p",
    "=p",
    ":-Þ",
    ":Þ",
    ":-b",
    ":b",
    ":-&",
    ">:p",
    ":-þ",
    ":þ"
  ],
  "terganggu": [
    ">:\\",
    ">:/",
    ":-/",
    ":-.",
    ":/",
    ":\\",
    "=/",
    "=\\",
    ":L",
    "=L",
    ":S",
    ">.<",
    ":-|",
    "<:-|",
    ".-:",
    "|-:",
    "|-:>",
    ":l",
    "=l",
    ":s"
  ],
  "bibir anjing laut": [":-X", ":X", ":-#", ":#", "#-:", "#:", ":-x"],
  "malaikat": [
    "O:-)",
    "0:-3",
    "0:3",
    "0:-)",
    "0:)",
    "0;^)",
    "(-:O",
    "(-:0",
    "(:0",
    "o:-)",
    "(-:o"
  ],
  "iblis": [
    ">:)",
    ">:D",
    ">:-D",
    ">;)",
    ">:-)",
    "}:-)",
    "}:)",
    "3:-)",
    "3:)",
    "(:<",
    "(-:<",
    "(-:{",
    "(:{",
    ">:d",
    ">:-d"
  ],
  "tos": ["o/\\o", "^5", ">_>^", "^<_<"],
  "hati": ["<3"]
}
